pytfrec/__init__.py
pytfrec/general.py
pytfrec/image.py
pytfrec-0.0.4.dist-info/LICENSE
pytfrec-0.0.4.dist-info/METADATA
pytfrec-0.0.4.dist-info/WHEEL
pytfrec-0.0.4.dist-info/top_level.txt
pytfrec-0.0.4.dist-info/RECORD
