Metadata-Version: 2.1
Name: pytfrec
Version: 0.0.4
Summary: Pythonic tools for TFRecord files
Home-page: https://github.com/dariush-bahrami/pytfrec
Author: dAriush Bahrami
Author-email: dariush.bahrami@ut.ac.ir
License: UNKNOWN
Platform: UNKNOWN
Classifier: Programming Language :: Python :: 3
Classifier: License :: OSI Approved :: GNU General Public License v3 (GPLv3)
Classifier: Operating System :: OS Independent
Requires-Python: >=3.6
